{
  "version": 1,
  "license_notes": "All bundled image references are placeholders that resolve to photos hosted by royalty-free, commercially-usable providers (Picsum / Unsplash / Pexels CDN). No image binaries are bundled in this repo. See README.md for per-provider licensing.",
  "images": [
    { "id": "img-abstract-001", "type": "image", "category": "abstract",  "name": "Soft amber blur",       "url": "https://picsum.photos/seed/rb-abstract-001/1200/800", "thumb": "https://picsum.photos/seed/rb-abstract-001/240/160", "license": "Unsplash", "source": "picsum", "w": 1200, "h": 800 },
    { "id": "img-abstract-002", "type": "image", "category": "abstract",  "name": "Cobalt swirls",         "url": "https://picsum.photos/seed/rb-abstract-002/1200/800", "thumb": "https://picsum.photos/seed/rb-abstract-002/240/160", "license": "Unsplash", "source": "picsum", "w": 1200, "h": 800 },
    { "id": "img-abstract-003", "type": "image", "category": "abstract",  "name": "Magenta wave",          "url": "https://picsum.photos/seed/rb-abstract-003/1200/800", "thumb": "https://picsum.photos/seed/rb-abstract-003/240/160", "license": "Unsplash", "source": "picsum", "w": 1200, "h": 800 },
    { "id": "img-abstract-004", "type": "image", "category": "abstract",  "name": "Teal mist",             "url": "https://picsum.photos/seed/rb-abstract-004/1200/800", "thumb": "https://picsum.photos/seed/rb-abstract-004/240/160", "license": "Unsplash", "source": "picsum", "w": 1200, "h": 800 },
    { "id": "img-abstract-005", "type": "image", "category": "abstract",  "name": "Glass shards",          "url": "https://picsum.photos/seed/rb-abstract-005/1200/800", "thumb": "https://picsum.photos/seed/rb-abstract-005/240/160", "license": "Unsplash", "source": "picsum", "w": 1200, "h": 800 },
    { "id": "img-abstract-006", "type": "image", "category": "abstract",  "name": "Solar flare",           "url": "https://picsum.photos/seed/rb-abstract-006/1200/800", "thumb": "https://picsum.photos/seed/rb-abstract-006/240/160", "license": "Unsplash", "source": "picsum", "w": 1200, "h": 800 },
    { "id": "img-abstract-007", "type": "image", "category": "abstract",  "name": "Liquid chrome",         "url": "https://picsum.photos/seed/rb-abstract-007/1200/800", "thumb": "https://picsum.photos/seed/rb-abstract-007/240/160", "license": "Unsplash", "source": "picsum", "w": 1200, "h": 800 },
    { "id": "img-abstract-008", "type": "image", "category": "abstract",  "name": "Pastel bloom",          "url": "https://picsum.photos/seed/rb-abstract-008/1200/800", "thumb": "https://picsum.photos/seed/rb-abstract-008/240/160", "license": "Unsplash", "source": "picsum", "w": 1200, "h": 800 },

    { "id": "img-texture-001",  "type": "image", "category": "texture",   "name": "Cracked stone",         "url": "https://picsum.photos/seed/rb-texture-001/1200/800", "thumb": "https://picsum.photos/seed/rb-texture-001/240/160", "license": "Unsplash", "source": "picsum", "w": 1200, "h": 800 },
    { "id": "img-texture-002",  "type": "image", "category": "texture",   "name": "Brushed metal",         "url": "https://picsum.photos/seed/rb-texture-002/1200/800", "thumb": "https://picsum.photos/seed/rb-texture-002/240/160", "license": "Unsplash", "source": "picsum", "w": 1200, "h": 800 },
    { "id": "img-texture-003",  "type": "image", "category": "texture",   "name": "Folded linen",          "url": "https://picsum.photos/seed/rb-texture-003/1200/800", "thumb": "https://picsum.photos/seed/rb-texture-003/240/160", "license": "Unsplash", "source": "picsum", "w": 1200, "h": 800 },
    { "id": "img-texture-004",  "type": "image", "category": "texture",   "name": "Concrete grain",        "url": "https://picsum.photos/seed/rb-texture-004/1200/800", "thumb": "https://picsum.photos/seed/rb-texture-004/240/160", "license": "Unsplash", "source": "picsum", "w": 1200, "h": 800 },
    { "id": "img-texture-005",  "type": "image", "category": "texture",   "name": "Weathered wood",        "url": "https://picsum.photos/seed/rb-texture-005/1200/800", "thumb": "https://picsum.photos/seed/rb-texture-005/240/160", "license": "Unsplash", "source": "picsum", "w": 1200, "h": 800 },
    { "id": "img-texture-006",  "type": "image", "category": "texture",   "name": "Bubble wrap",           "url": "https://picsum.photos/seed/rb-texture-006/1200/800", "thumb": "https://picsum.photos/seed/rb-texture-006/240/160", "license": "Unsplash", "source": "picsum", "w": 1200, "h": 800 },

    { "id": "img-nature-001",   "type": "image", "category": "nature",    "name": "Mountain ridge",        "url": "https://picsum.photos/seed/rb-nature-001/1200/800", "thumb": "https://picsum.photos/seed/rb-nature-001/240/160", "license": "Unsplash", "source": "picsum", "w": 1200, "h": 800 },
    { "id": "img-nature-002",   "type": "image", "category": "nature",    "name": "Calm shoreline",        "url": "https://picsum.photos/seed/rb-nature-002/1200/800", "thumb": "https://picsum.photos/seed/rb-nature-002/240/160", "license": "Unsplash", "source": "picsum", "w": 1200, "h": 800 },
    { "id": "img-nature-003",   "type": "image", "category": "nature",    "name": "Sunset field",          "url": "https://picsum.photos/seed/rb-nature-003/1200/800", "thumb": "https://picsum.photos/seed/rb-nature-003/240/160", "license": "Unsplash", "source": "picsum", "w": 1200, "h": 800 },
    { "id": "img-nature-004",   "type": "image", "category": "nature",    "name": "Forest canopy",         "url": "https://picsum.photos/seed/rb-nature-004/1200/800", "thumb": "https://picsum.photos/seed/rb-nature-004/240/160", "license": "Unsplash", "source": "picsum", "w": 1200, "h": 800 },
    { "id": "img-nature-005",   "type": "image", "category": "nature",    "name": "Desert dunes",          "url": "https://picsum.photos/seed/rb-nature-005/1200/800", "thumb": "https://picsum.photos/seed/rb-nature-005/240/160", "license": "Unsplash", "source": "picsum", "w": 1200, "h": 800 },
    { "id": "img-nature-006",   "type": "image", "category": "nature",    "name": "Tropical leaves",       "url": "https://picsum.photos/seed/rb-nature-006/1200/800", "thumb": "https://picsum.photos/seed/rb-nature-006/240/160", "license": "Unsplash", "source": "picsum", "w": 1200, "h": 800 },
    { "id": "img-nature-007",   "type": "image", "category": "nature",    "name": "Snowy peak",            "url": "https://picsum.photos/seed/rb-nature-007/1200/800", "thumb": "https://picsum.photos/seed/rb-nature-007/240/160", "license": "Unsplash", "source": "picsum", "w": 1200, "h": 800 },
    { "id": "img-nature-008",   "type": "image", "category": "nature",    "name": "Foggy lake",            "url": "https://picsum.photos/seed/rb-nature-008/1200/800", "thumb": "https://picsum.photos/seed/rb-nature-008/240/160", "license": "Unsplash", "source": "picsum", "w": 1200, "h": 800 },

    { "id": "img-people-001",   "type": "image", "category": "people",    "name": "Portrait — warm light", "url": "https://picsum.photos/seed/rb-people-001/1200/800", "thumb": "https://picsum.photos/seed/rb-people-001/240/160", "license": "Unsplash", "source": "picsum", "w": 1200, "h": 800 },
    { "id": "img-people-002",   "type": "image", "category": "people",    "name": "Group meeting",         "url": "https://picsum.photos/seed/rb-people-002/1200/800", "thumb": "https://picsum.photos/seed/rb-people-002/240/160", "license": "Unsplash", "source": "picsum", "w": 1200, "h": 800 },
    { "id": "img-people-003",   "type": "image", "category": "people",    "name": "Hands at work",         "url": "https://picsum.photos/seed/rb-people-003/1200/800", "thumb": "https://picsum.photos/seed/rb-people-003/240/160", "license": "Unsplash", "source": "picsum", "w": 1200, "h": 800 },
    { "id": "img-people-004",   "type": "image", "category": "people",    "name": "City walker",           "url": "https://picsum.photos/seed/rb-people-004/1200/800", "thumb": "https://picsum.photos/seed/rb-people-004/240/160", "license": "Unsplash", "source": "picsum", "w": 1200, "h": 800 },
    { "id": "img-people-005",   "type": "image", "category": "people",    "name": "Studio smile",          "url": "https://picsum.photos/seed/rb-people-005/1200/800", "thumb": "https://picsum.photos/seed/rb-people-005/240/160", "license": "Unsplash", "source": "picsum", "w": 1200, "h": 800 },
    { "id": "img-people-006",   "type": "image", "category": "people",    "name": "Workshop team",         "url": "https://picsum.photos/seed/rb-people-006/1200/800", "thumb": "https://picsum.photos/seed/rb-people-006/240/160", "license": "Unsplash", "source": "picsum", "w": 1200, "h": 800 },

    { "id": "img-product-001",  "type": "image", "category": "product",   "name": "Coffee on table",       "url": "https://picsum.photos/seed/rb-product-001/1200/800", "thumb": "https://picsum.photos/seed/rb-product-001/240/160", "license": "Unsplash", "source": "picsum", "w": 1200, "h": 800 },
    { "id": "img-product-002",  "type": "image", "category": "product",   "name": "Headphones flatlay",    "url": "https://picsum.photos/seed/rb-product-002/1200/800", "thumb": "https://picsum.photos/seed/rb-product-002/240/160", "license": "Unsplash", "source": "picsum", "w": 1200, "h": 800 },
    { "id": "img-product-003",  "type": "image", "category": "product",   "name": "Sneaker on concrete",   "url": "https://picsum.photos/seed/rb-product-003/1200/800", "thumb": "https://picsum.photos/seed/rb-product-003/240/160", "license": "Unsplash", "source": "picsum", "w": 1200, "h": 800 },
    { "id": "img-product-004",  "type": "image", "category": "product",   "name": "Ceramic mug",           "url": "https://picsum.photos/seed/rb-product-004/1200/800", "thumb": "https://picsum.photos/seed/rb-product-004/240/160", "license": "Unsplash", "source": "picsum", "w": 1200, "h": 800 },
    { "id": "img-product-005",  "type": "image", "category": "product",   "name": "Watch close-up",        "url": "https://picsum.photos/seed/rb-product-005/1200/800", "thumb": "https://picsum.photos/seed/rb-product-005/240/160", "license": "Unsplash", "source": "picsum", "w": 1200, "h": 800 },
    { "id": "img-product-006",  "type": "image", "category": "product",   "name": "Skincare bottles",      "url": "https://picsum.photos/seed/rb-product-006/1200/800", "thumb": "https://picsum.photos/seed/rb-product-006/240/160", "license": "Unsplash", "source": "picsum", "w": 1200, "h": 800 },

    { "id": "img-tech-001",     "type": "image", "category": "tech",      "name": "Server rack blue",      "url": "https://picsum.photos/seed/rb-tech-001/1200/800", "thumb": "https://picsum.photos/seed/rb-tech-001/240/160", "license": "Unsplash", "source": "picsum", "w": 1200, "h": 800 },
    { "id": "img-tech-002",     "type": "image", "category": "tech",      "name": "Code on screen",        "url": "https://picsum.photos/seed/rb-tech-002/1200/800", "thumb": "https://picsum.photos/seed/rb-tech-002/240/160", "license": "Unsplash", "source": "picsum", "w": 1200, "h": 800 },
    { "id": "img-tech-003",     "type": "image", "category": "tech",      "name": "Workstation",           "url": "https://picsum.photos/seed/rb-tech-003/1200/800", "thumb": "https://picsum.photos/seed/rb-tech-003/240/160", "license": "Unsplash", "source": "picsum", "w": 1200, "h": 800 },
    { "id": "img-tech-004",     "type": "image", "category": "tech",      "name": "Circuit macro",         "url": "https://picsum.photos/seed/rb-tech-004/1200/800", "thumb": "https://picsum.photos/seed/rb-tech-004/240/160", "license": "Unsplash", "source": "picsum", "w": 1200, "h": 800 },
    { "id": "img-tech-005",     "type": "image", "category": "tech",      "name": "Phone in hand",         "url": "https://picsum.photos/seed/rb-tech-005/1200/800", "thumb": "https://picsum.photos/seed/rb-tech-005/240/160", "license": "Unsplash", "source": "picsum", "w": 1200, "h": 800 },
    { "id": "img-tech-006",     "type": "image", "category": "tech",      "name": "Dark keyboard",         "url": "https://picsum.photos/seed/rb-tech-006/1200/800", "thumb": "https://picsum.photos/seed/rb-tech-006/240/160", "license": "Unsplash", "source": "picsum", "w": 1200, "h": 800 },

    { "id": "img-pattern-001",  "type": "image", "category": "pattern",   "name": "Geometric tiles",       "url": "https://picsum.photos/seed/rb-pattern-001/1200/800", "thumb": "https://picsum.photos/seed/rb-pattern-001/240/160", "license": "Unsplash", "source": "picsum", "w": 1200, "h": 800 },
    { "id": "img-pattern-002",  "type": "image", "category": "pattern",   "name": "Hex grid",              "url": "https://picsum.photos/seed/rb-pattern-002/1200/800", "thumb": "https://picsum.photos/seed/rb-pattern-002/240/160", "license": "Unsplash", "source": "picsum", "w": 1200, "h": 800 },
    { "id": "img-pattern-003",  "type": "image", "category": "pattern",   "name": "Dotted weave",          "url": "https://picsum.photos/seed/rb-pattern-003/1200/800", "thumb": "https://picsum.photos/seed/rb-pattern-003/240/160", "license": "Unsplash", "source": "picsum", "w": 1200, "h": 800 },
    { "id": "img-pattern-004",  "type": "image", "category": "pattern",   "name": "Stripes bold",          "url": "https://picsum.photos/seed/rb-pattern-004/1200/800", "thumb": "https://picsum.photos/seed/rb-pattern-004/240/160", "license": "Unsplash", "source": "picsum", "w": 1200, "h": 800 },
    { "id": "img-pattern-005",  "type": "image", "category": "pattern",   "name": "Chevron muted",         "url": "https://picsum.photos/seed/rb-pattern-005/1200/800", "thumb": "https://picsum.photos/seed/rb-pattern-005/240/160", "license": "Unsplash", "source": "picsum", "w": 1200, "h": 800 },
    { "id": "img-pattern-006",  "type": "image", "category": "pattern",   "name": "Terrazzo chips",        "url": "https://picsum.photos/seed/rb-pattern-006/1200/800", "thumb": "https://picsum.photos/seed/rb-pattern-006/240/160", "license": "Unsplash", "source": "picsum", "w": 1200, "h": 800 }
  ],

  "gifs": [],

  "gradients": [
    { "id": "grad-aurora",     "type": "gradient", "name": "Aurora",     "category": "vibrant", "css": "linear-gradient(135deg, #00d2ff 0%, #3a47d5 100%)" },
    { "id": "grad-sunset",     "type": "gradient", "name": "Sunset",     "category": "warm",    "css": "linear-gradient(135deg, #ff6e7f 0%, #bfe9ff 100%)" },
    { "id": "grad-mint",       "type": "gradient", "name": "Mint",       "category": "cool",    "css": "linear-gradient(135deg, #00b09b 0%, #96c93d 100%)" },
    { "id": "grad-cosmic",     "type": "gradient", "name": "Cosmic",     "category": "dark",    "css": "linear-gradient(135deg, #0f2027 0%, #203a43 50%, #2c5364 100%)" },
    { "id": "grad-peach",      "type": "gradient", "name": "Peach",      "category": "warm",    "css": "linear-gradient(135deg, #ffecd2 0%, #fcb69f 100%)" },
    { "id": "grad-deepsea",    "type": "gradient", "name": "Deep sea",   "category": "dark",    "css": "linear-gradient(135deg, #2E3192 0%, #1BFFFF 100%)" },
    { "id": "grad-flame",      "type": "gradient", "name": "Flame",      "category": "vibrant", "css": "linear-gradient(135deg, #f12711 0%, #f5af19 100%)" },
    { "id": "grad-lavender",   "type": "gradient", "name": "Lavender",   "category": "cool",    "css": "linear-gradient(135deg, #c471f5 0%, #fa71cd 100%)" },
    { "id": "grad-paper",      "type": "gradient", "name": "Paper",      "category": "neutral", "css": "linear-gradient(135deg, #f5f7fa 0%, #c3cfe2 100%)" },
    { "id": "grad-emerald",    "type": "gradient", "name": "Emerald",    "category": "cool",    "css": "linear-gradient(135deg, #11998e 0%, #38ef7d 100%)" },
    { "id": "grad-coal",       "type": "gradient", "name": "Coal",       "category": "neutral", "css": "linear-gradient(135deg, #232526 0%, #414345 100%)" },
    { "id": "grad-rose",       "type": "gradient", "name": "Rose",       "category": "warm",    "css": "linear-gradient(135deg, #ffafbd 0%, #ffc3a0 100%)" }
  ]
}